trytond/modules/health_federation/COPYING
trytond/modules/health_federation/README.rst
trytond/modules/health_federation/__init__.py
trytond/modules/health_federation/data/federation_objects.xml
trytond/modules/health_federation/data/gnuhealth_commands.xml
trytond/modules/health_federation/data/messages/messages.xml
trytond/modules/health_federation/exceptions.py
trytond/modules/health_federation/health_federation.py
trytond/modules/health_federation/health_federation_view.xml
trytond/modules/health_federation/locale/ar.po
trytond/modules/health_federation/locale/de.po
trytond/modules/health_federation/locale/el.po
trytond/modules/health_federation/locale/eo.po
trytond/modules/health_federation/locale/es.po
trytond/modules/health_federation/locale/fr.po
trytond/modules/health_federation/locale/health_federation.pot
trytond/modules/health_federation/locale/it_IT.po
trytond/modules/health_federation/locale/ja_JP.po
trytond/modules/health_federation/locale/ka.po
trytond/modules/health_federation/locale/lo.po
trytond/modules/health_federation/locale/pt_BR.po
trytond/modules/health_federation/locale/sv.po
trytond/modules/health_federation/locale/tr.po
trytond/modules/health_federation/locale/uk.po
trytond/modules/health_federation/locale/zh_CN.po
trytond/modules/health_federation/pyproject.toml
trytond/modules/health_federation/security/access_rights.xml
trytond/modules/health_federation/tests/__init__.py
trytond/modules/health_federation/tests/test_health_federation.py
trytond/modules/health_federation/tryton.cfg
trytond/modules/health_federation/view/gnuhealth_federation_config.xml
trytond/modules/health_federation/view/gnuhealth_federation_config_tree.xml
trytond/modules/health_federation/view/gnuhealth_federation_object.xml
trytond/modules/health_federation/view/gnuhealth_federation_object_tree.xml
trytond/modules/health_federation/view/gnuhealth_federation_queue.xml
trytond/modules/health_federation/view/gnuhealth_federation_queue_tree.xml
gnuhealth_federation-5.0.2.dist-info/METADATA
gnuhealth_federation-5.0.2.dist-info/WHEEL
gnuhealth_federation-5.0.2.dist-info/licenses/COPYING
gnuhealth_federation-5.0.2.dist-info/RECORD
